llwy/__init__.py
llwy/__main__.py
llwy/llwy.py
llwy-0.0.3.dist-info/licenses/LICENSE
llwy-0.0.3.dist-info/METADATA
llwy-0.0.3.dist-info/WHEEL
llwy-0.0.3.dist-info/top_level.txt
llwy-0.0.3.dist-info/RECORD
