Metadata-Version: 2.4
Name: llwy
Version: 0.0.3
Summary: init
Home-page: https://github.com/
Author: lhqvq
Author-email: lhqvq@mail.ustc.edu.cn
Classifier: Programming Language :: Python :: 3
Classifier: License :: OSI Approved :: MIT License
Classifier: Operating System :: OS Independent
License-File: LICENSE
Dynamic: author
Dynamic: author-email
Dynamic: classifier
Dynamic: description
Dynamic: home-page
Dynamic: license-file
Dynamic: summary
